Piya/Sonar/Echo.py
Piya/Sonar/Echos.py
Piya/Sonar/IOEvent.py
Piya/Sonar/__init__.py
Piya.Sonar-0.1.1.dist-info/LICENSE.txt
Piya.Sonar-0.1.1.dist-info/METADATA
Piya.Sonar-0.1.1.dist-info/WHEEL
Piya.Sonar-0.1.1.dist-info/top_level.txt
Piya.Sonar-0.1.1.dist-info/RECORD
