Metadata-Version: 2.1
Name: Piya.Sonar
Version: 0.1.1
Summary: Ultrasonic HC-SR04 Sensor echo lib.
Home-page: https://github.com/apiyap/piya_echo
Author: Piya Pimchankam
Author-email: piya.pimchankam@gmail.com
License: MIT
Keywords: Jetson HC-SR04 Sensor Echo
Platform: UNKNOWN
Classifier: Operating System :: POSIX :: Linux
Classifier: License :: OSI Approved :: MIT License
Classifier: Intended Audience :: Developers
Classifier: Programming Language :: Python :: 2.7
Classifier: Programming Language :: Python :: 3
Classifier: Topic :: Software Development
Classifier: Topic :: System :: Hardware
Requires-Dist: Jetson.GPIO
